pyisbn/__init__.py
pyisbn/_constants.py
pyisbn/_exceptions.py
pyisbn/_types.py
pyisbn/_utils.py
pyisbn/func.py
pyisbn/models.py
pyisbn-1.4.1.dist-info/licenses/COPYING
pyisbn-1.4.1.dist-info/WHEEL
pyisbn-1.4.1.dist-info/METADATA
pyisbn-1.4.1.dist-info/RECORD
