Metadata-Version: 2.4
Name: pyisbn
Version: 1.4.1
Summary: A module for working with 10- and 13-digit ISBNs
Keywords: ISBN,ISBN-10,ISBN-13,SBN
Author: James Rowe
Author-email: James Rowe <jnrowe@gmail.com>
License-Expression: GPL-3.0-or-later
License-File: COPYING
Classifier: Development Status :: 6 - Mature
Classifier: Intended Audience :: Developers
Classifier: Intended Audience :: Other Audience
Classifier: License :: OSI Approved
Classifier: License :: OSI Approved :: GNU General Public License (GPL)
Classifier: License :: OSI Approved :: GNU General Public License v3 or later (GPLv3+)
Classifier: Operating System :: OS Independent
Classifier: Programming Language :: Python
Classifier: Programming Language :: Python :: 3
Classifier: Programming Language :: Python :: 3.11
Classifier: Programming Language :: Python :: 3.12
Classifier: Programming Language :: Python :: 3.13
Classifier: Programming Language :: Python :: 3.14
Classifier: Topic :: Other/Nonlisted Topic
Classifier: Topic :: Software Development :: Libraries
Classifier: Topic :: Software Development :: Libraries :: Python Modules
Classifier: Topic :: Text Processing
Classifier: Topic :: Text Processing :: Indexing
Requires-Python: >=3.11
Project-URL: Changelog, https://github.com/JNRowe/pyisbn/blob/main/NEWS.rst
Project-URL: Contributors, https://github.com/JNRowe/pyisbn/contributors/
Project-URL: Documentation, https://pyisbn.readthedocs.io/
Project-URL: Git repository, https://github.com/JNRowe/pyisbn/
Project-URL: Issue tracker, https://github.com/JNRowe/pyisbn/issues/
Project-URL: Source code, https://github.com/JNRowe/pyisbn
